neuralcache/__init__.py
neuralcache/cli.py
neuralcache/config.py
neuralcache/embedding.py
neuralcache/encoder.py
neuralcache/gating.py
neuralcache/narrative.py
neuralcache/pheromone.py
neuralcache/rerank.py
neuralcache/similarity.py
neuralcache/types.py
neuralcache/version.py
neuralcache/adapters/__init__.py
neuralcache/adapters/langchain_adapter.py
neuralcache/adapters/llamaindex_adapter.py
neuralcache/api/server.py
neuralcache/api/server_plus.py
neuralcache/cr/cli.py
neuralcache/cr/index.py
neuralcache/cr/search.py
neuralcache/cr/utils.py
neuralcache/metrics/__init__.py
neuralcache/metrics/prom.py
neuralcache/metrics/text.py
neuralcache/storage/sqlite_state.py
neuralcache-0.3.2.dist-info/licenses/LICENSE
neuralcache-0.3.2.dist-info/METADATA
neuralcache-0.3.2.dist-info/WHEEL
neuralcache-0.3.2.dist-info/entry_points.txt
neuralcache-0.3.2.dist-info/top_level.txt
neuralcache-0.3.2.dist-info/RECORD
