Metadata-Version: 2.4
Name: neuralcache
Version: 0.3.2
Summary: NeuralCache: narrative + stigmergic reranker for RAG (Context-Use@K uplift).
Author-email: Carnot Engine <hello@carnotengine.com>
License-Expression: Apache-2.0
Keywords: RAG,reranker,LLM,information retrieval,narrative coherence,stigmergy
Classifier: Programming Language :: Python :: 3
Classifier: Programming Language :: Python :: 3 :: Only
Classifier: Programming Language :: Python :: 3.11
Classifier: Programming Language :: Python :: 3.12
Classifier: Operating System :: OS Independent
Requires-Python: >=3.11
License-File: LICENSE
Requires-Dist: fastapi<0.121,>=0.118
Requires-Dist: starlette<0.51,>=0.48
Requires-Dist: uvicorn[standard]<0.32,>=0.30
Requires-Dist: numpy>=1.26
Requires-Dist: pydantic>=2.6
Requires-Dist: pydantic-settings>=2.2
Requires-Dist: scipy>=1.11
Requires-Dist: typer>=0.12
Requires-Dist: orjson>=3.9
Requires-Dist: python-dateutil>=2.9
Requires-Dist: rich>=13.7
Provides-Extra: test
Requires-Dist: pytest>=8.0; extra == "test"
Requires-Dist: pytest-cov>=5.0; extra == "test"
Provides-Extra: dev
Requires-Dist: ruff>=0.4; extra == "dev"
Requires-Dist: mypy>=1.8; extra == "dev"
Requires-Dist: pre-commit>=3.6; extra == "dev"
Requires-Dist: httpx>=0.27; extra == "dev"
Requires-Dist: types-requests>=2.32; extra == "dev"
Provides-Extra: embeddings
Requires-Dist: openai>=1.0.0; extra == "embeddings"
Requires-Dist: sentence-transformers>=2.6.0; extra == "embeddings"
Provides-Extra: ops
Requires-Dist: prometheus-client>=0.20; extra == "ops"
Requires-Dist: requests>=2.32; extra == "ops"
Provides-Extra: adapters
Requires-Dist: langchain-core>=0.2; extra == "adapters"
Requires-Dist: llama-index-core>=0.10; extra == "adapters"
Dynamic: license-file
